Compiled from "SingletonDCL.java"
public class com.nowcoder.designPattern.SingletonPattern.SingletonDCL {
  public static com.nowcoder.designPattern.SingletonPattern.SingletonDCL getSingleton();
    Code:
       0: getstatic     #2                  // Field singleton:Lcom/nowcoder/designPattern/SingletonPattern/SingletonDCL;
       3: ifnonnull     37
       6: ldc           #3                  // class com/nowcoder/designPattern/SingletonPattern/SingletonDCL
       8: dup
       9: astore_0
      10: monitorenter
      11: getstatic     #2                  // Field singleton:Lcom/nowcoder/designPattern/SingletonPattern/SingletonDCL;
      14: ifnonnull     27
      17: new           #3                  // class com/nowcoder/designPattern/SingletonPattern/SingletonDCL
      20: dup
      21: invokespecial #4                  // Method "<init>":()V
      24: putstatic     #2                  // Field singleton:Lcom/nowcoder/designPattern/SingletonPattern/SingletonDCL;
      27: aload_0
      28: monitorexit
      29: goto          37
      32: astore_1
      33: aload_0
      34: monitorexit
      35: aload_1
      36: athrow
      37: getstatic     #2                  // Field singleton:Lcom/nowcoder/designPattern/SingletonPattern/SingletonDCL;
      40: areturn
    Exception table:
       from    to  target type
          11    29    32   any
          32    35    32   any

  public static void main(java.lang.String[]);
    Code:
       0: invokestatic  #5                  // Method getSingleton:()Lcom/nowcoder/designPattern/SingletonPattern/SingletonDCL;
       3: astore_1
       4: invokestatic  #5                  // Method getSingleton:()Lcom/nowcoder/designPattern/SingletonPattern/SingletonDCL;
       7: astore_2
       8: new           #3                  // class com/nowcoder/designPattern/SingletonPattern/SingletonDCL
      11: dup
      12: invokespecial #4                  // Method "<init>":()V
      15: astore_3
      16: getstatic     #6                  // Field java/lang/System.out:Ljava/io/PrintStream;
      19: aload_1
      20: aload_2
      21: if_acmpne     28
      24: iconst_1
      25: goto          29
      28: iconst_0
      29: invokevirtual #7                  // Method java/io/PrintStream.println:(Z)V
      32: getstatic     #6                  // Field java/lang/System.out:Ljava/io/PrintStream;
      35: aload_1
      36: aload_3
      37: if_acmpne     44
      40: iconst_1
      41: goto          45
      44: iconst_0
      45: invokevirtual #7                  // Method java/io/PrintStream.println:(Z)V
      48: getstatic     #6                  // Field java/lang/System.out:Ljava/io/PrintStream;
      51: aload_1
      52: invokevirtual #8                  // Method java/io/PrintStream.println:(Ljava/lang/Object;)V
      55: return
}
